venv_pack/__init__.py
venv_pack/__main__.py
venv_pack/core.py
venv_pack/formats.py
venv_pack/progress.py
venv_pack/scripts/CPYTHON_LICENSE.txt
venv_pack/scripts/common/Activate.ps1
venv_pack/scripts/common/activate
venv_pack/scripts/nt/activate.bat
venv_pack2-0.9.1.dist-info/LICENSE.txt
venv_pack2-0.9.1.dist-info/METADATA
venv_pack2-0.9.1.dist-info/WHEEL
venv_pack2-0.9.1.dist-info/entry_points.txt
venv_pack2-0.9.1.dist-info/top_level.txt
venv_pack2-0.9.1.dist-info/RECORD
