Metadata-Version: 2.1
Name: venv-pack2
Version: 0.9.1
Summary: Package virtual environments for redistribution
Maintainer-email: mrmathematica <mrmathematica@yahoo.com>
Project-URL: Repository, https://github.com/mrmathematica/venv-pack2.git
Keywords: venv,packaging,portable
Classifier: Topic :: System :: Archiving :: Packaging
Classifier: Topic :: System :: Software Distribution
Classifier: Topic :: Software Development :: Build Tools
Classifier: License :: OSI Approved :: BSD License
Classifier: Programming Language :: Python :: 3
License-File: LICENSE.txt
